pyapi/client/__init__.py
pyapi/client/py.typed
pyapi/client/spec.py
pyapi/client/wrappers.py
pyapi_client-0.3.1.dist-info/WHEEL
pyapi_client-0.3.1.dist-info/METADATA
pyapi_client-0.3.1.dist-info/RECORD
