Metadata-Version: 2.1
Name: pyapi-client
Version: 0.3.1
Summary: Python client library for making requests to any OpenAPI-based service.
License: MIT
Author-email: Berislav Lopac <berislav@lopac.net>
Requires-Python: >=3.10
Requires-Dist: PyYAML>=5.4
Requires-Dist: httpx>=0.22
Requires-Dist: jsonschema-path>=0.3.3
Requires-Dist: openapi-core>=0.16.1
Requires-Dist: stringcase>=1.2.0
Project-URL: documentation, https://pyapi-client.readthedocs.io
Project-URL: homepage, https://pyapi-client.readthedocs.io
Project-URL: repository, https://github.com/berislavlopac/pyapi-client
